LICENSE
README.md
setup.py
pyml_toolbox/__init__.py
pyml_toolbox.egg-info/PKG-INFO
pyml_toolbox.egg-info/SOURCES.txt
pyml_toolbox.egg-info/dependency_links.txt
pyml_toolbox.egg-info/requires.txt
pyml_toolbox.egg-info/top_level.txt
pyml_utils/__init__.py
pyml_utils/conf.py
pyml_utils/engines.py
pyml_utils/files.py
pyml_utils/logger.py