Metadata-Version: 2.1
Name: pyml-toolbox
Version: 0.1.0
Summary: A machine learning toolbox and utility functions
Home-page: https://github.com/toomasu13/pyml_toolbox
Author: Toomas Kirt
Author-email: Toomas.Kirt@gmail.com
License: GNU GPLv3
Classifier: Development Status :: 2 - Pre-Alpha
Classifier: Intended Audience :: Science/Research
Classifier: Intended Audience :: Developers
Classifier: License :: OSI Approved :: GNU General Public License v3 (GPLv3)
Classifier: Operating System :: POSIX :: Linux
Classifier: Programming Language :: Python :: 3
Classifier: Programming Language :: Python :: 3.7
Classifier: Programming Language :: Python :: 3.8
Classifier: Programming Language :: Python :: 3.9
Classifier: Programming Language :: Python :: 3.10
License-File: LICENSE
